maptide-0.4.0.dist-info/METADATA
maptide-0.4.0.dist-info/WHEEL
maptide-0.4.0.dist-info/entry_points.txt
maptide-0.4.0.dist-info/licenses/LICENSE
maptide/cli.py
maptide/api.py
maptide/__init__.py
maptide/maptide.abi3.so
maptide-0.4.0.dist-info/RECORD
