Metadata-Version: 2.4
Name: maptide
Version: 0.4.0
Classifier: License :: OSI Approved :: MIT License
Classifier: Programming Language :: Python :: 3.9
Classifier: Programming Language :: Python :: 3.10
Classifier: Programming Language :: Python :: 3.11
Classifier: Programming Language :: Python :: 3.12
Classifier: Programming Language :: Python :: 3.13
Classifier: Programming Language :: Rust
License-File: LICENSE
Summary: Base frequencies for BAM files
Keywords: bioinformatics,pileup,base-frequency
Author-email: Thomas Brier <t.o.brier@bham.ac.uk>
Maintainer-email: Thomas Brier <t.o.brier@bham.ac.uk>
License: MIT
Requires-Python: >=3.9
Project-URL: repository, https://github.com/CLIMB-COVID/maptide
